[
  {
    "ig_id": "17844478518694868",
    "date": "2026-03-14",
    "type": "single",
    "image": "17844478518694868.jpg",
    "caption": "🎵 이번 주 멜론 차트 TOP 5!\n\n1위 🏆 BANG BANG — 404 (New Era)\n2위 🔥 RUDE! — Drowning\n3위 💜 사랑하게 될 거야 — BLACKHOLE\n4위 ✨ Good Goodbye — GO\n5위 🎶 0+0 — Blue Valentine\n\n이번 주 뭐 들을지 고민이라면? 👇\n👉 dalkonnect.com/charts\n\n#멜론차트 #KPop #케이팝 #달커넥트 #DalKonnect #달라스한인 #DFW한인 #KoreanMusic #KoreanDallas #재미교포 #한국음악 #케이팝차트",
    "timestamp": "2026-03-14T21:48:58+0000"
  },
  {
    "ig_id": "17997825425745372",
    "date": "2026-03-14",
    "type": "carousel",
    "images": [
      "17997825425745372_slide_0.jpg",
      "17997825425745372_slide_1.jpg",
      "17997825425745372_slide_2.jpg",
      "17997825425745372_slide_3.jpg",
      "17997825425745372_slide_4.jpg",
      "17997825425745372_slide_5.jpg"
    ],
    "caption": "💡 달라스 한인 생활 꿀팁 2편!\n\n달라스에서 더 스마트하게 사는 법 👆 슬라이드 넘겨보세요!\n\n🗣️ 영어 못해도 달라스에서 살 수 있어요\n🏥 병원 & 보험 이렇게 활용하세요\n🚗 텍사스 운전면허 빨리 따는 법\n🛒 달라스 쇼핑 스마트하게 하는 법\n\n👉 더 많은 DFW 한인 정보: dalkonnect.com\n📱 저장하고 주변에 공유해주세요!\n\n#달라스꿀팁 #달라스한인 #DFW한인 #달라스생활 #달라스이민 #달커넥트 #DalKonnect #텍사스한인 #KoreanDallas #재미교포 #달라스정착 #달라스정보",
    "timestamp": "2026-03-14T21:08:52+0000"
  },
  {
    "ig_id": "18105543421867832",
    "date": "2026-03-14",
    "type": "single",
    "image": "18105543421867832.jpg",
    "caption": "🦷 이주의 달라스 업소 스팟라이트!\n\n✨ @saysmiledental — SaySmile Dental\n📍 Frisco, TX · Nuri Kim, DDS (한인 원장)\n\n⭐ 5.0 별점 · 리뷰 239개\n한국어 가능한 DFW 치과 🏆\n\n일반 치과 · 임플란트 · 미백 · 교정\n📞 (972) 525-4900\n🌐 saysmiledental.com\n\n👉 달커넥트에서 DFW 한인 병원/치과 찾기\ndalkonnect.com/businesses\n\n#달라스치과 #한인치과 #SaySmile #Frisco치과 #달라스한인 #DFW한인 #달커넥트 #DalKonnect #KoreanDentist #재미교포 #달라스병원",
    "timestamp": "2026-03-14T21:07:27+0000"
  },
  {
    "ig_id": "17957133615063592",
    "date": "2026-03-14",
    "type": "single",
    "image": "17957133615063592.jpg",
    "caption": "💅 이주의 달라스 업소 스팟라이트!\n\n✨ @shenailbartx — She Nail Bar\n📍 Dallas, TX\n\n⭐ 5.0 별점 · 리뷰 797개\n달라스 한인 No.1 네일샵 💅\n\n젤네일 · 아크릴 · 네일아트 전문\n📞 (214) 613-2030\n🌐 shenailbartx.com\n\n👉 달커넥트에서 더 많은 DFW 한인 업소 찾기\ndalkonnect.com/businesses\n\n#달라스네일 #달라스네일샵 #SheNailBar #달라스한인 #DFW한인 #달커넥트 #DalKonnect #KoreanDallas #달라스미용 #재미교포 #달라스뷰티",
    "timestamp": "2026-03-14T21:07:02+0000"
  },
  {
    "ig_id": "17877991650531695",
    "date": "2026-03-14",
    "type": "single",
    "image": "17877991650531695.jpg",
    "caption": "📸 이주의 달라스 업소 스팟라이트!\n\n✨ @clickittexas — Clickit Self-photo Studio\n📍 Carrollton, TX\n\n⭐ 5.0 별점 · 리뷰 1,435개\n달라스 No.1 셀프 사진관 🏆\n\n혼자서도, 친구들과도, 커플도 OK!\n가족사진 · 생일 · 졸업 · 커플 · 패션 촬영\n\n📞 (469) 444-0917\n🌐 clickittexas.com\n\n👉 달커넥트에서 더 많은 DFW 한인 업소 찾기\ndalkonnect.com/businesses\n\n#달라스사진관 #셀프사진관 #달라스한인 #DFW한인 #Carrollton #달커넥트 #DalKonnect #달라스데이트 #달라스커플 #KoreanDallas #DFWKorean #달라스맛집 #달라스생활 #재미교포",
    "timestamp": "2026-03-14T21:03:32+0000"
  },
  {
    "ig_id": "18053591699488941",
    "date": "2026-03-14",
    "type": "single",
    "image": "18053591699488941.jpg",
    "caption": "🎬 이번 주 한국 박스오피스 TOP 5!\n\n1위 👑 왕과 사는 남자 (22만명)\n2위 🔥 삼악도 (8,864명)\n3위 🎬 F1 더 무비 (6,977명)\n4위 🕵️ 휴민트 (4,308명)\n5위 ⚔️ 극장판 진격의 거인 (4,225명)\n\n이번 주 뭐 볼지 고민이라면? 👇\n👉 dalkonnect.com/charts\n\n#한국박스오피스 #한국영화 #영화차트 #달커넥트 #DalKonnect #달라스한인 #DFW한인 #KoreanMovie #KoreanDallas #재미교포",
    "timestamp": "2026-03-14T18:38:54+0000"
  },
  {
    "ig_id": "18048357869713724",
    "date": "2026-03-14",
    "type": "carousel",
    "images": [
      "18048357869713724_slide_0.jpg",
      "18048357869713724_slide_1.jpg",
      "18048357869713724_slide_2.jpg",
      "18048357869713724_slide_3.jpg",
      "18048357869713724_slide_4.jpg",
      "18048357869713724_slide_5.jpg",
      "18048357869713724_slide_6.jpg"
    ],
    "caption": "🍽️ DFW 달라스 한인 맛집 TOP 5!\n\n달커넥트 실제 리뷰 기반 한인 식당 베스트 🔥\n\n🥇 Chicken Barn — Frisco ⭐4.9 (리뷰 1,356개)\n🥈 Gold Spoon 금수저 — Carrollton ⭐4.9\n🥉 Hong Dumpling House — Dallas ⭐4.9\n4️⃣ Dol dol Mara — Plano ⭐5.0\n5️⃣ Geupshik — Lewisville ⭐5.0\n\n더 많은 DFW 한인 식당 👇\n👉 dalkonnect.com/businesses\n\n#달라스맛집 #DFW맛집 #달라스한식 #달라스한인 #DFW한인 #달커넥트 #DalKonnect #KoreanFood #KoreanDallas #달라스식당 #재미교포",
    "timestamp": "2026-03-14T18:23:12+0000"
  },
  {
    "ig_id": "18096611002989458",
    "date": "2026-03-14",
    "type": "carousel",
    "images": [
      "18096611002989458_slide_0.jpg",
      "18096611002989458_slide_1.jpg",
      "18096611002989458_slide_2.jpg",
      "18096611002989458_slide_3.jpg",
      "18096611002989458_slide_4.jpg",
      "18096611002989458_slide_5.jpg"
    ],
    "caption": "🇰🇷🤠 달라스 한인 필수 꿀팁 5가지!\n\n달라스 처음 오셨나요? 아니면 더 잘 살고 싶으세요?\n알면 달라지는 달라스 생활 꿀팁 모았어요 👆 슬라이드 넘겨보세요!\n\n✅ 운전면허 빨리 따는 법\n✅ H-Mart 말고도 있는 한인마트\n✅ 한인 커뮤니티 찾는 법\n✅ 의료·행정 미리 준비하기\n\n👉 더 많은 달라스 한인 정보: dalkonnect.com\n📱 팔로우하고 저장해두세요!\n\n#달라스한인 #DFW한인 #달라스생활 #달라스꿀팁 #달라스정착 #달라스이민 #달커넥트 #DalKonnect #텍사스한인 #KoreanDallas #DFWKorean #재미교포 #달라스맘",
    "timestamp": "2026-03-14T18:13:49+0000"
  },
  {
    "ig_id": "18082292351608477",
    "date": "2026-03-14",
    "type": "single",
    "image": "18082292351608477.jpg",
    "caption": "진천 가정집서 강도 행각 벌이고 도주한 3인조 일당 구속 영장\n\n경찰이 가정집에 침입해 강도 행각을 벌인 일당에 대한 구속 영장을 신청했다.충북 진천경찰서는 특수강도 혐의로 50대 A 씨 등 3명에 대해 구속 영장을 신청했다고 14일 밝혔다.A 씨 등은 지난 9일 오전 10시 10분쯤 진천군 초평면 한 단독주택에서 B 씨(80대·여...\n\n자세히 보기 👉 dalkonnect.com/news\n\n#달커넥트 #한국뉴스 #KPOP #DalConnect #KoreanNews #달라스한인 #DFW한인 #달라스 #달커넥트",
    "timestamp": "2026-03-14T17:29:30+0000"
  },
  {
    "ig_id": "17869439775581754",
    "date": "2026-03-14",
    "type": "single",
    "image": "17869439775581754.jpg",
    "caption": "달라스 러브 필드에서 TSA 요원 2명 폭행 및 달라스 경찰관 부상 혐의로 기소된 남성\n\n33세 남성이 달라스 러브 필드에서 TSA 요원을 폭행하고 달라스 경찰관에게 부상을 입힌 혐의로 연방 당국에 의해 구금되었습니다....\n\n자세히 보기 👉 dalkonnect.com/news\n\n#달커넥트 #DFW한인 #달라스뉴스 #DalConnect #DFWKorean #DallasNews #달라스한인 #DFW한인 #달라스 #달커넥트",
    "timestamp": "2026-03-14T17:29:10+0000"
  },
  {
    "ig_id": "18076707026110440",
    "date": "2026-03-14",
    "type": "single",
    "image": "18076707026110440.jpg",
    "caption": "최신 포브스 억만장자 명단에 텍사스 주민 다수 포함\n\n총 80명 이상의 텍사스 주민이 잡지의 최신 지구상 부자 명단에 이름을 올렸으며, 그중 42명은 노스 텍사스 출신입니다....\n\n자세히 보기 👉 dalkonnect.com/news\n\n#달커넥트 #DFW한인 #달라스뉴스 #DalConnect #DFWKorean #DallasNews #달라스한인 #DFW한인 #달라스 #달커넥트",
    "timestamp": "2026-03-14T17:28:50+0000"
  },
  {
    "ig_id": "18456154084098356",
    "date": "2026-03-14",
    "type": "carousel",
    "images": [
      "18456154084098356_slide_0.jpg",
      "18456154084098356_slide_1.jpg",
      "18456154084098356_slide_2.jpg",
      "18456154084098356_slide_3.jpg"
    ],
    "caption": "🇰🇷🤠 달커넥트(DalKonnect)에 오신 것을 환영합니다!\n\n달라스-포트워스 한인 커뮤니티를 위한 종합 포털입니다.\n\n📍 한인 업소록 1,168개\n📰 DFW 로컬뉴스 + 한국 소식 매일 업데이트\n🎵 K-컬쳐 차트 (음악·드라마·영화·유튜브)\n🛍️ 사고팔기 · 공동구매 딜 · 커뮤니티\n\n달라스 한인의 모든 것, 한 곳에서 👇\n🔗 dalkonnect.com (링크 in bio)\n\n#달커넥트 #DalKonnect #달라스한인 #DFW한인 #달라스 #텍사스한인 #DFWKorean #KoreanDallas #달라스맛집 #달라스업소록",
    "timestamp": "2026-03-14T14:32:33+0000"
  },
  {
    "ig_id": "18003334952855439",
    "date": "2026-03-14",
    "type": "single",
    "image": "18003334952855439.jpg",
    "caption": "🇰🇷🤠 달라스 한인 여러분 환영합니다!\n\nDFW에 사는 한인 여러분을 위해\n달커넥트가 함께합니다 🙌\n\n팔로우하고 함께해요 👆\n\n👉 dalkonnect.com (링크 in bio)\n\n#달커넥트 #DalKonnect #달라스한인 #DFW한인 #달라스 #텍사스한인 #DFWKorean #KoreanDallas",
    "timestamp": "2026-03-14T14:31:21+0000"
  },
  {
    "ig_id": "17985237788952849",
    "date": "2026-03-14",
    "type": "single",
    "image": "17985237788952849.jpg",
    "caption": "📍 DFW 한인 업소 1,168개!\n\n한식당🍽️ 미용실💇 병원🏥 교회⛪\n마트🛒 부동산🏠 법률⚖️ 태권도🥋\n\n👉 dalkonnect.com (링크 in bio)\n\n#달라스한인 #DFW한인업소 #달라스맛집 #달커넥트 #DalKonnect #달라스",
    "timestamp": "2026-03-14T14:30:47+0000"
  },
  {
    "ig_id": "18412846315120938",
    "date": "2026-03-14",
    "type": "single",
    "image": "18412846315120938.jpg",
    "caption": "💭 우리가 달커넥트를 만든 이유\n\n달라스 처음 왔을 때\n정보 찾기가 너무 힘들었어요.\n\n그래서 만들었습니다 🙌\n\n👉 dalkonnect.com (링크 in bio)\n\n#달라스한인 #DFW한인 #달라스이민 #달커넥트 #DalKonnect #텍사스한인",
    "timestamp": "2026-03-14T14:29:30+0000"
  },
  {
    "ig_id": "17997192038867384",
    "date": "2026-03-14",
    "type": "single",
    "image": "17997192038867384.jpg",
    "caption": "📰 뉴스 + 🎵 K-차트, 달커넥트에서!\n\n달라스 뉴스 + 한국 소식 매일 업데이트\n음악·드라마·영화 순위도 매일!\n\n👉 dalkonnect.com (링크 in bio)\n\n#달라스뉴스 #KPOP #한국드라마 #넷플릭스 #달커넥트 #DalKonnect",
    "timestamp": "2026-03-14T14:28:54+0000"
  },
  {
    "ig_id": "18097649254797948",
    "date": "2026-03-14",
    "type": "single",
    "image": "18097649254797948.jpg",
    "caption": "🤝 달라스 한인 커뮤니티 공간!\n\n💬자유게시판 🛍️사고팔기 🏷️딜 📍업체등록\n\n함께 만들어가는 DFW 한인 공간 🇰🇷\n\n👉 dalkonnect.com (링크 in bio)\n\n#달라스한인 #DFW한인 #달라스사고팔기 #달커넥트 #DalKonnect",
    "timestamp": "2026-03-14T14:28:18+0000"
  },
  {
    "ig_id": "18023117582815508",
    "date": "2026-03-14",
    "type": "single",
    "image": "18023117582815508.jpg",
    "caption": "🏪 달라스 사업자분들!\n달커넥트에 무료로 업소 등록하세요 👆\n\n✅무료 📍지도노출 👥1,168개 업소 이미 등록 중\n\n👉 dalkonnect.com/businesses (링크 in bio)\n\n#달라스한인업소 #달라스비즈니스 #달커넥트 #DFW한인 #달라스",
    "timestamp": "2026-03-14T14:27:39+0000"
  },
  {
    "ig_id": "18162498325421997",
    "date": "2026-03-14",
    "type": "single",
    "image": "18162498325421997.jpg",
    "caption": "🗺️ 달라스 한인의 구글맵 + 커뮤니티!\n\n한인병원 · 뉴스 · 사고팔기 · 맛집 · 차트\n모두 달커넥트 하나로!\n\n👉 dalkonnect.com (링크 in bio)\n\n#달커넥트 #DalKonnect #달라스한인 #DFW #텍사스한인",
    "timestamp": "2026-03-14T14:27:02+0000"
  },
  {
    "ig_id": "17861767227610612",
    "date": "2026-03-14",
    "type": "single",
    "image": "17861767227610612.jpg",
    "caption": "💡 달커넥트 이렇게 쓰세요!\n\n🔍업소찾기 📰뉴스 🛍️사고팔기 🏷️딜 🎵차트\n\n👉 dalkonnect.com (링크 in bio)\n\n#달커넥트 #DalKonnect #달라스한인 #DFW한인 #달라스",
    "timestamp": "2026-03-14T14:26:26+0000"
  }
]